RNN4IE-0.1.0.dist-info/METADATA
RNN4IE-0.1.0.dist-info/RECORD
RNN4IE-0.1.0.dist-info/WHEEL
RNN4IE-0.1.0.dist-info/top_level.txt
RNN4IE-0.1.0.dist-info/zip-safe
dset/__init__.py
dset/get_dataset.py
log/__init__.py
model/__init__.py
rnn4ie/__init__.py
rnn4ie/gru/__init__.py
rnn4ie/gru/model.py
rnn4ie/gru/predict.py
rnn4ie/gru/train.py
rnn4ie/gru_mhsa/__init__.py
rnn4ie/gru_mhsa/model.py
rnn4ie/gru_mhsa/predict.py
rnn4ie/gru_mhsa/train.py
rnn4ie/gru_sa/__init__.py
rnn4ie/gru_sa/model.py
rnn4ie/gru_sa/predict.py
rnn4ie/gru_sa/train.py
rnn4ie/gru_xca/__init__.py
rnn4ie/gru_xca/model.py
rnn4ie/gru_xca/predict.py
rnn4ie/gru_xca/train.py
rnn4ie/util/__init__.py
rnn4ie/util/crf.py
rnn4ie/util/crf_util.py
rnn4ie/util/define_loss.py
rnn4ie/util/define_optimizer.py
rnn4ie/util/metrics.py
rnn4ie/util/model_util.py
