Metadata-Version: 2.1
Name: RNN4IE
Version: 0.1.0
Summary: Chinese Information Extraction
Home-page: https://github.com/jiangnanboy/RNN4IE
Author: ShiYan
Author-email: 2229029156@qq.com
License: Apache 2.0
Keywords: NLP,IE,Chinese Information Extraction
Platform: Windows
Platform: Linux
Platform: Solaris
Platform: Mac OS-X
Platform: Unix
Classifier: Intended Audience :: Developers
Classifier: Operating System :: OS Independent
Classifier: Natural Language :: Chinese (Simplified)
Classifier: Natural Language :: Chinese (Traditional)
Classifier: Programming Language :: Python
Classifier: Programming Language :: Python :: 3
Classifier: Programming Language :: Python :: 3.6
Classifier: Topic :: Text Processing :: Linguistic
Classifier: Topic :: Scientific/Engineering :: Artificial Intelligence
Requires-Python: >=3.6
